storedsafe/__init__.py
storedsafe-1.3.0.dist-info/METADATA
storedsafe-1.3.0.dist-info/WHEEL
storedsafe-1.3.0.dist-info/licenses/COPYING
storedsafe-1.3.0.dist-info/RECORD
