Metadata-Version: 2.4
Name: storedsafe
Version: 1.3.0
Summary: Wrapper for the StoredSafe REST-like API.
Project-URL: Homepage, https://github.com/storedsafe/storedsafe-python
Project-URL: Issues, https://github.com/storedsafe/storedsafe-python/issues
Author-email: Oscar Mattsson <oscar@storedsafe.com>
License-File: COPYING
Classifier: License :: OSI Approved :: GNU Affero General Public License v3 or later (AGPLv3+)
Classifier: Operating System :: OS Independent
Classifier: Programming Language :: Python :: 3
Requires-Python: >=3.6
